rocky/__init__.py
rocky/argparse.py
rocky/config.py
rocky/process.py
rocky/syspath.py
rocky-1.0.2.dist-info/LICENSE
rocky-1.0.2.dist-info/METADATA
rocky-1.0.2.dist-info/WHEEL
rocky-1.0.2.dist-info/top_level.txt
rocky-1.0.2.dist-info/RECORD
